decneo/__init__.py
decneo/analysisPipeline.py
decneo/commonFunctions.py
decneo/general.py
decneo/genes.py
decneo/supplementaryFunctions.py
decneo/__pycache__/__init__.cpython-38.pyc
decneo/__pycache__/analysisPipeline.cpython-38.pyc
decneo/__pycache__/commonFunctions.cpython-38.pyc
decneo/__pycache__/general.cpython-38.pyc
decneo/__pycache__/genes.cpython-38.pyc
decneo/__pycache__/supplementaryFunctions.cpython-38.pyc
decneo/geneLists/Age.xlsx
decneo/geneLists/Baumeister_lig_rec.txt
decneo/geneLists/Co-signalling molecules SD.xlsx
decneo/geneLists/HGNC_receptors.txt
decneo/geneLists/Mouse_to_Human_HUGO.gz
decneo/geneLists/PanglaoDBtissues.xlsx
decneo/geneLists/Pardoll_lig_rec.txt
decneo/geneLists/Rate.xlsx
decneo/geneLists/TF_1.01_HUGO.txt
decneo/geneLists/TranscriptionFactors_DatabaseExtract_v_1.01.xlsx
decneo/geneLists/__init__.py
decneo/geneLists/cd_marker_handbook.xlsx
decneo/geneLists/common strongest Endothelial markes.txt
decneo/geneLists/eye.xlsx
decneo/geneLists/eye_correlated_markers.xlsx
decneo/geneLists/eye_correlated_markers_heart.xlsx
decneo/geneLists/fibro_endo_epi.xlsx
decneo/geneLists/fibro_endo_epi_v2_Human.xlsx
decneo/geneLists/fibro_endo_epi_v2_Mouse.xlsx
decneo/geneLists/fibro_endo_epi_v2_pre.xlsx
decneo/geneLists/hemostasis_genes.txt
decneo/geneLists/ligands_1777.txt
decneo/geneLists/ligands_44.txt
decneo/geneLists/ligands_Human_HUGO.txt
decneo/geneLists/positive-negative-GO.xlsx
decneo/geneLists/receptorsListHugo_2555.txt
decneo/geneLists/receptors_Human_HUGO.txt
decneo/geneLists/stalk.txt
decneo/geneLists/tip.txt
decneo/geneLists/__pycache__/__init__.cpython-38.pyc
decneo-1.0.7.dist-info/LICENSE
decneo-1.0.7.dist-info/METADATA
decneo-1.0.7.dist-info/WHEEL
decneo-1.0.7.dist-info/top_level.txt
decneo-1.0.7.dist-info/RECORD
