Metadata-Version: 2.1
Name: decneo
Version: 1.0.7
Summary: Comberons from single cell transcriptomics in endothelial cells
Home-page: https://github.com/sdomanskyi/decneo
Author: S. Domanskyi, A. Hakansson, M. Meng, J. S. Graff Zivin, C. Piermarocchi, G. Paternostro, N. Ferrara
Author-email: s.domanskyi@gmail.com
License: MIT License
Platform: UNKNOWN
Classifier: License :: OSI Approved :: MIT License
Classifier: Programming Language :: Python :: 3
Classifier: Topic :: Scientific/Engineering :: Bio-Informatics
Classifier: Intended Audience :: Science/Research
Classifier: Intended Audience :: Education
Classifier: Intended Audience :: Developers
Classifier: Intended Audience :: End Users/Desktop
Classifier: Operating System :: MacOS
Classifier: Operating System :: Microsoft :: Windows
Classifier: Operating System :: Unix
Classifier: Topic :: Education
Classifier: Topic :: Utilities
Requires-Python: >=3
Requires-Dist: numpy (>=1.19.1)
Requires-Dist: pandas (>=1.0.1)
Requires-Dist: patsy (>=0.5.1)
Requires-Dist: xlrd (>=1.2.0)
Requires-Dist: openpyxl (>=3.0.3)
Requires-Dist: tables (>=3.6.1)
Requires-Dist: scipy (>=1.4.1)
Requires-Dist: matplotlib (>=3.1.3)
Requires-Dist: scikit-learn (>=0.22.1)
Requires-Dist: networkx (>=2.4)
Requires-Dist: adjustText (>=0.7.3)
